struqture_py-2.3.2.dist-info/METADATA
struqture_py-2.3.2.dist-info/WHEEL
struqture_py-2.3.2.dist-info/licenses/LICENSE
struqture_py/DEPENDENCIES
struqture_py/LICENSE_FOR_BINARY_DISTRIBUTION
struqture_py/PYTHON_LICENSE
struqture_py/__init__.py
struqture_py/bosons.pyi
struqture_py/fermions.pyi
struqture_py/mixed_systems.pyi
struqture_py/spins.pyi
struqture_py/struqture_py.cpython-39-x86_64-linux-gnu.so
struqture_py/struqture_py.pyi
struqture_py-2.3.2.dist-info/RECORD
